traju/__init__.py
traju/cli.py
traju/helpers.py
traju/traju.py
traju-0.1.0.dist-info/entry_points.txt
traju-0.1.0.dist-info/LICENSE
traju-0.1.0.dist-info/WHEEL
traju-0.1.0.dist-info/METADATA
traju-0.1.0.dist-info/RECORD
